pypartpicker/__init__.py
pypartpicker/regex.py
pypartpicker/scraper.py
pypartpicker2-0.1.9.dist-info/LICENSE.txt
pypartpicker2-0.1.9.dist-info/METADATA
pypartpicker2-0.1.9.dist-info/WHEEL
pypartpicker2-0.1.9.dist-info/top_level.txt
pypartpicker2-0.1.9.dist-info/RECORD
