Metadata-Version: 2.1
Name: pypartpicker2
Version: 0.1.9
Summary: A package that scrapes pcpartpicker.com and returns the results as objects.
Home-page: https://github.com/giuseppe99barchetta/pypartpicker
Download-URL: https://github.com/giuseppe99barchetta/pypartpicker/archive/refs/tags/0.1.6.tar.gz
Keywords: pcpartpicker,scraper,list,beautifulsoup,pc,parts
Classifier: Development Status :: 5 - Production/Stable
Classifier: Intended Audience :: Developers
Classifier: Topic :: Software Development :: Build Tools
Classifier: License :: OSI Approved :: MIT License
Classifier: Programming Language :: Python :: 3.7
Classifier: Programming Language :: Python :: 3.8
Classifier: Programming Language :: Python :: 3.9
Classifier: Programming Language :: Python :: 3.10
Classifier: Programming Language :: Python :: 3.11
License-File: LICENSE.txt
Requires-Dist: bs4
Requires-Dist: requests
